topsis/TOPSIS3410.py
Topsis_Ranker-1.0.3.dist-info/LICENSE
Topsis_Ranker-1.0.3.dist-info/METADATA
Topsis_Ranker-1.0.3.dist-info/WHEEL
Topsis_Ranker-1.0.3.dist-info/entry_points.txt
Topsis_Ranker-1.0.3.dist-info/top_level.txt
Topsis_Ranker-1.0.3.dist-info/RECORD
