Metadata-Version: 2.1
Name: Topsis-Ranker
Version: 1.0.3
Summary: A python package to get topsis rank of given dataset
Home-page: https://github.com/PulkitKhagta/Topsis-Pyhton-Package
Author: Pulkit Khagta
Author-email: khagtapulkit@gmail.com
License: MIT
Platform: UNKNOWN
Classifier: License :: OSI Approved :: MIT License
Classifier: Programming Language :: Python :: 3
Classifier: Programming Language :: Python :: 3.7
Requires-Dist: requests
